music_sampler/__init__.py
music_sampler/action.py
music_sampler/actions/__init__.py
music_sampler/actions/comment.py
music_sampler/actions/interrupt_wait.py
music_sampler/actions/load_music.py
music_sampler/actions/pause.py
music_sampler/actions/pause_wait.py
music_sampler/actions/play.py
music_sampler/actions/reset_wait.py
music_sampler/actions/run_command.py
music_sampler/actions/seek.py
music_sampler/actions/stop.py
music_sampler/actions/stop_all_actions.py
music_sampler/actions/unload_music.py
music_sampler/actions/unpause.py
music_sampler/actions/unpause_wait.py
music_sampler/actions/volume.py
music_sampler/actions/wait.py
music_sampler/app.py
music_sampler/app_blocks/__init__.py
music_sampler/app_blocks/actionlist.py
music_sampler/app_blocks/playlist.py
music_sampler/helpers.py
music_sampler/key.py
music_sampler/locales/fr/LC_MESSAGES/music_sampler.mo
music_sampler/locales/fr/LC_MESSAGES/music_sampler.po
music_sampler/lock.py
music_sampler/mapping.py
music_sampler/mixer.py
music_sampler/music_effect.py
music_sampler/music_file.py
music_sampler/music_sampler.kv
music_sampler/sysfont.py
music_sampler-1.7.0.dist-info/METADATA
music_sampler-1.7.0.dist-info/WHEEL
music_sampler-1.7.0.dist-info/entry_points.txt
music_sampler-1.7.0.dist-info/RECORD
